atsbindings/__init__.py
atsbindings/bindings.py
atsbindings/board_specific_info.toml
atsbindings/enumerations.py
atsbindings-0.2.3.dist-info/licenses/LICENSE
atsbindings-0.2.3.dist-info/METADATA
atsbindings-0.2.3.dist-info/WHEEL
atsbindings-0.2.3.dist-info/top_level.txt
atsbindings-0.2.3.dist-info/RECORD
