Metadata-Version: 2.4
Name: atsbindings
Version: 0.2.3
Summary: Bindings for Alazar digitizer boards
Author-email: "T. D. Weber" <tweber@mit.edu>
License: MIT
Project-URL: Homepage, https://github.com/tweber225/atsbindings
Classifier: Programming Language :: Python :: 3
Classifier: Programming Language :: Python :: 3.7
Classifier: Programming Language :: Python :: 3.8
Classifier: Programming Language :: Python :: 3.9
Classifier: Programming Language :: Python :: 3.10
Classifier: Programming Language :: Python :: 3.11
Classifier: Programming Language :: Python :: 3.12
Classifier: Programming Language :: Python :: 3.13
Classifier: License :: OSI Approved :: MIT License
Classifier: Operating System :: Microsoft :: Windows
Classifier: Topic :: System :: Hardware
Requires-Python: >=3.7
License-File: LICENSE
Requires-Dist: numpy>=1.21.0
Dynamic: license-file
